chinillaclvm_tools_rs-0.1.28.dist-info/METADATA
chinillaclvm_tools_rs-0.1.28.dist-info/WHEEL
chinillaclvm_tools_rs/__init__.py
chinillaclvm_tools_rs/chinillaclvm_tools_rs.pyd
chinillaclvm_tools_rs-0.1.28.dist-info/RECORD
