Metadata-Version: 2.1
Name: chinillaclvm_tools_rs
Version: 0.1.28
Summary: tools for working with chinillalisp language; compiler, repl, python and wasm bindings
Keywords: chinilla,chinillalisp,chinillaclvm
Home-Page: https://prozacchiwawa.github.io/chinillaclvm_tools_rs/
Author: Art Yerkes <art.yerkes@gmail.com>
Author-email: Art Yerkes <art.yerkes@gmail.com>
License: Apache-2.0
Project-URL: Source Code, https://github.com/Chinilla/chinillaclvm_tools_rs
